Metadata-Version: 2.1
Name: Troika-TB
Version: 0.0.5
Summary: A pipeline implementing TB-Profiler for batch detection and reporting of anti-microbial resistance in TB for public health and clinical use.
Home-page: https://github.com/kristyhoran/troika
Author: Kristy Horan
Author-email: kristyhoran15@gmail.com
License: UNKNOWN
Platform: UNKNOWN
Classifier: Programming Language :: Python :: 3.7
Classifier: Operating System :: OS Independent
Classifier: Development Status :: 4 - Beta
Classifier: Intended Audience :: Science/Research
Classifier: Topic :: Scientific/Engineering :: Bio-Informatics
Classifier: License :: OSI Approved :: GNU General Public License v3 (GPLv3)
Requires-Python: >=3.7
Requires-Dist: pytest
Requires-Dist: jinja2
Requires-Dist: biopython (>=1.70)
Requires-Dist: pandas (>=0.23.0)
Requires-Dist: numpy
Requires-Dist: svgwrite
Requires-Dist: psutil
Requires-Dist: sh
Requires-Dist: packaging
Requires-Dist: snakemake (>=5.9.1)
Requires-Dist: configargparse
Requires-Dist: xlsxwriter
Provides-Extra: tests
Requires-Dist: pytest ; extra == 'tests'
Requires-Dist: flake8 ; extra == 'tests'
